README.md
setup.py
model_dataset/__init__.py
model_dataset.egg-info/PKG-INFO
model_dataset.egg-info/SOURCES.txt
model_dataset.egg-info/dependency_links.txt
model_dataset.egg-info/requires.txt
model_dataset.egg-info/top_level.txt