Metadata-Version: 2.1
Name: model_dataset
Version: 1.0.0
Summary: A light weight command line menu that supports Windows, MacOS, and Linux
Author: clever chen
Author-email: 
Keywords: python,add,windows,mac,linux
Classifier: Development Status :: 1 - Planning
Classifier: Intended Audience :: Developers
Classifier: Programming Language :: Python :: 3
Classifier: Operating System :: Unix
Classifier: Operating System :: MacOS :: MacOS X
Classifier: Operating System :: Microsoft :: Windows
Requires-Dist: numpy
Requires-Dist: torch
